plotly_resampler/__init__.py
plotly_resampler/aggregation/__init__.py
plotly_resampler/aggregation/aggregation_interface.py
plotly_resampler/aggregation/aggregators.py
plotly_resampler/aggregation/algorithms/lttbc.cpython-310-x86_64-linux-gnu.so
plotly_resampler/aggregation/gap_handler_interface.py
plotly_resampler/aggregation/gap_handlers.py
plotly_resampler/aggregation/plotly_aggregator_parser.py
plotly_resampler/figure_resampler/__init__.py
plotly_resampler/figure_resampler/assets/coarse_fine.js
plotly_resampler/figure_resampler/figure_resampler.py
plotly_resampler/figure_resampler/figure_resampler_interface.py
plotly_resampler/figure_resampler/figurewidget_resampler.py
plotly_resampler/figure_resampler/jupyter_dash_persistent_inline_output.py
plotly_resampler/figure_resampler/utils.py
plotly_resampler/registering.py
plotly_resampler-0.9.2.dist-info/LICENSE
plotly_resampler-0.9.2.dist-info/METADATA
plotly_resampler-0.9.2.dist-info/WHEEL
plotly_resampler-0.9.2.dist-info/RECORD
