Metadata-Version: 2.1
Name: plotly-resampler
Version: 0.9.2
Summary: Visualizing large time series with plotly
Home-page: https://github.com/predict-idlab/plotly-resampler
License: MIT
Keywords: time-series,visualization,resampling,plotly,plotly-dash
Author: Jonas Van Der Donckt
Requires-Python: >=3.7.1,<4.0.0
Classifier: Development Status :: 5 - Production/Stable
Classifier: Intended Audience :: Developers
Classifier: License :: OSI Approved :: MIT License
Classifier: Operating System :: MacOS :: MacOS X
Classifier: Operating System :: Microsoft :: Windows
Classifier: Operating System :: POSIX :: Linux
Classifier: Programming Language :: Python
Classifier: Programming Language :: Python :: 3
Classifier: Programming Language :: Python :: 3.8
Classifier: Programming Language :: Python :: 3.9
Classifier: Programming Language :: Python :: 3.10
Classifier: Programming Language :: Python :: 3.11
Classifier: Programming Language :: Python :: 3.12
Classifier: Programming Language :: Python :: 3.7
Provides-Extra: inline-persistent
Requires-Dist: Flask-Cors (>=3.0.10,<4.0.0) ; extra == "inline-persistent"
Requires-Dist: dash (>=2.9.0)
Requires-Dist: jupyter-dash (>=0.4.2) ; extra == "inline-persistent"
Requires-Dist: kaleido (==0.2.1) ; extra == "inline-persistent"
Requires-Dist: numpy (>=1.14) ; python_version < "3.11"
Requires-Dist: numpy (>=1.24) ; python_version >= "3.11"
Requires-Dist: orjson (>=3.8.0,<4.0.0)
Requires-Dist: pandas (>=1)
Requires-Dist: plotly (>=5.5.0,<6.0.0)
Requires-Dist: tsdownsample (==0.1.2)
Project-URL: Documentation, https://predict-idlab.github.io/plotly-resampler/latest
Project-URL: Repository, https://github.com/predict-idlab/plotly-resampler
